backwardsreg/__init__.py
backwardsreg/backward_regression.py
tests/__init__.py
tests/test_backward_regression.py
backwardsreg-0.1.dist-info/LICENSE.txt
backwardsreg-0.1.dist-info/METADATA
backwardsreg-0.1.dist-info/WHEEL
backwardsreg-0.1.dist-info/entry_points.txt
backwardsreg-0.1.dist-info/top_level.txt
backwardsreg-0.1.dist-info/RECORD
